setup.py
boxdotcom/__init__.py
boxdotcom.egg-info/PKG-INFO
boxdotcom.egg-info/SOURCES.txt
boxdotcom.egg-info/dependency_links.txt
boxdotcom.egg-info/top_level.txt