Metadata-Version: 1.0
Name: boxdotcom
Version: 0.2.1
Summary: Python wrapper for Box.com/.net API
Home-page: http://github.com/dvska/python-boxdotcom
Author: Sean Rose
Author-email: sean.andrew.rose@gmail.com
License: Apache License
Keywords: python,box,box.net,box.com,api,wrapper
Platform: UNKNOWN
Classifier: Programming Language :: Python
Classifier: Development Status :: 4 - Beta
Classifier: Environment :: Other Environment
Classifier: Intended Audience :: Developers
Classifier: License :: OSI Approved
Classifier: Operating System :: OS Independent
Classifier: Topic :: Software Development :: Libraries :: Python Modules
Classifier: Topic :: Software Development
